// class version 52.0 (52)
// access flags 0x21
public class com/github/kornilova_l/flamegraph/javaagent/generate/test_classes/HasCatch {


  // access flags 0x1
  public <init>()V
    ALOAD 0
    INVOKESPECIAL java/lang/Object.<init> ()V
    RETURN
    MAXSTACK = 1
    MAXLOCALS = 1

  // access flags 0x9
  public static main([Ljava/lang/String;)V
    TRYCATCHBLOCK L0 L1 L2 java/lang/Throwable
    TRYCATCHBLOCK L3 L4 L5 java/lang/Throwable
    TRYCATCHBLOCK L3 L4 L6 null
    TRYCATCHBLOCK L7 L8 L9 java/lang/Throwable
    TRYCATCHBLOCK L5 L10 L6 null
    TRYCATCHBLOCK L11 L12 L13 java/io/IOException
    TRYCATCHBLOCK L11 L14 L14 java/lang/Throwable
    INVOKESTATIC java/lang/System.currentTimeMillis ()J
    ACONST_NULL
    INVOKESTATIC com/github/kornilova_l/flamegraph/javaagent/logger/LoggerQueue.createStartData (J[Ljava/lang/Object;)Lcom/github/kornilova_l/flamegraph/proxy/StartData;
    ASTORE 1
   L11
    NEW java/io/FileOutputStream
    DUP
    NEW java/io/File
    DUP
    LDC ""
    INVOKESPECIAL java/io/File.<init> (Ljava/lang/String;)V
    INVOKESPECIAL java/io/FileOutputStream.<init> (Ljava/io/File;)V
    ASTORE 2
    ACONST_NULL
    ASTORE 3
   L3
    ALOAD 2
    ICONST_0
    NEWARRAY T_BYTE
    INVOKEVIRTUAL java/io/OutputStream.write ([B)V
   L4
    ALOAD 2
    IFNULL L12
    ALOAD 3
    IFNULL L15
   L0
    ALOAD 2
    INVOKEVIRTUAL java/io/OutputStream.close ()V
   L1
    GOTO L12
   L2
   FRAME FULL [[Ljava/lang/String; com/github/kornilova_l/flamegraph/proxy/StartData java/io/FileOutputStream N] [java/lang/Throwable]
    ASTORE 4
    ALOAD 3
    ALOAD 4
    INVOKEVIRTUAL java/lang/Throwable.addSuppressed (Ljava/lang/Throwable;)V
    GOTO L12
   L15
   FRAME SAME
    ALOAD 2
    INVOKEVIRTUAL java/io/OutputStream.close ()V
    GOTO L12
   L5
   FRAME SAME1 java/lang/Throwable
    ASTORE 4
    ALOAD 4
    ASTORE 3
    ALOAD 4
    ALOAD 1
    INVOKESTATIC java/lang/System.currentTimeMillis ()J
    INVOKEVIRTUAL com/github/kornilova_l/flamegraph/proxy/StartData.setDuration (J)V
    ALOAD 1
    INVOKEVIRTUAL com/github/kornilova_l/flamegraph/proxy/StartData.setThrownByMethod ()V
    ALOAD 1
    INVOKEVIRTUAL com/github/kornilova_l/flamegraph/proxy/StartData.getDuration ()J
    LCONST_1
    LCMP
    IFLE L16
    DUP
    ICONST_1
    ALOAD 1
    INVOKEVIRTUAL com/github/kornilova_l/flamegraph/proxy/StartData.getStartTime ()J
    ALOAD 1
    INVOKEVIRTUAL com/github/kornilova_l/flamegraph/proxy/StartData.getDuration ()J
    ALOAD 1
    INVOKEVIRTUAL com/github/kornilova_l/flamegraph/proxy/StartData.getParameters ()[Ljava/lang/Object;
    INVOKESTATIC java/lang/Thread.currentThread ()Ljava/lang/Thread;
    LDC "com/github/kornilova_l/flamegraph/javaagent/generate/test_classes/HasCatch"
    LDC "main"
    LDC "([Ljava/lang/String;)V"
    ICONST_1
    LDC ""
    INVOKESTATIC com/github/kornilova_l/flamegraph/javaagent/logger/LoggerQueue.addToQueue (Ljava/lang/Throwable;ZJJ[Ljava/lang/Object;Ljava/lang/Thread;Ljava/lang/String;Ljava/lang/String;Ljava/lang/String;ZLjava/lang/String;)V
   L16
   FRAME FULL [[Ljava/lang/String; com/github/kornilova_l/flamegraph/proxy/StartData java/io/FileOutputStream java/lang/Throwable java/lang/Throwable] [java/lang/Throwable]
    ATHROW
   L6
   FRAME FULL [[Ljava/lang/String; com/github/kornilova_l/flamegraph/proxy/StartData java/io/FileOutputStream java/lang/Throwable] [java/lang/Throwable]
    ASTORE 5
   L10
    ALOAD 2
    IFNULL L17
    ALOAD 3
    IFNULL L18
   L7
    ALOAD 2
    INVOKEVIRTUAL java/io/OutputStream.close ()V
   L8
    GOTO L17
   L9
   FRAME FULL [[Ljava/lang/String; com/github/kornilova_l/flamegraph/proxy/StartData java/io/FileOutputStream java/lang/Throwable T java/lang/Throwable] [java/lang/Throwable]
    ASTORE 6
    ALOAD 3
    ALOAD 6
    INVOKEVIRTUAL java/lang/Throwable.addSuppressed (Ljava/lang/Throwable;)V
    GOTO L17
   L18
   FRAME SAME
    ALOAD 2
    INVOKEVIRTUAL java/io/OutputStream.close ()V
   L17
   FRAME SAME
    ALOAD 5
    ALOAD 1
    INVOKESTATIC java/lang/System.currentTimeMillis ()J
    INVOKEVIRTUAL com/github/kornilova_l/flamegraph/proxy/StartData.setDuration (J)V
    ALOAD 1
    INVOKEVIRTUAL com/github/kornilova_l/flamegraph/proxy/StartData.setThrownByMethod ()V
    ALOAD 1
    INVOKEVIRTUAL com/github/kornilova_l/flamegraph/proxy/StartData.getDuration ()J
    LCONST_1
    LCMP
    IFLE L19
    DUP
    ICONST_1
    ALOAD 1
    INVOKEVIRTUAL com/github/kornilova_l/flamegraph/proxy/StartData.getStartTime ()J
    ALOAD 1
    INVOKEVIRTUAL com/github/kornilova_l/flamegraph/proxy/StartData.getDuration ()J
    ALOAD 1
    INVOKEVIRTUAL com/github/kornilova_l/flamegraph/proxy/StartData.getParameters ()[Ljava/lang/Object;
    INVOKESTATIC java/lang/Thread.currentThread ()Ljava/lang/Thread;
    LDC "com/github/kornilova_l/flamegraph/javaagent/generate/test_classes/HasCatch"
    LDC "main"
    LDC "([Ljava/lang/String;)V"
    ICONST_1
    LDC ""
    INVOKESTATIC com/github/kornilova_l/flamegraph/javaagent/logger/LoggerQueue.addToQueue (Ljava/lang/Throwable;ZJJ[Ljava/lang/Object;Ljava/lang/Thread;Ljava/lang/String;Ljava/lang/String;Ljava/lang/String;ZLjava/lang/String;)V
   L19
   FRAME SAME1 java/lang/Throwable
    ATHROW
   L12
   FRAME FULL [[Ljava/lang/String; com/github/kornilova_l/flamegraph/proxy/StartData java/io/FileOutputStream N] []
    GOTO L20
   L13
   FRAME FULL [[Ljava/lang/String; com/github/kornilova_l/flamegraph/proxy/StartData] [java/io/IOException]
    ASTORE 2
    ALOAD 2
    INVOKEVIRTUAL java/io/IOException.printStackTrace ()V
   L20
   FRAME APPEND [java/lang/Object]
    ALOAD 1
    INVOKESTATIC java/lang/System.currentTimeMillis ()J
    INVOKEVIRTUAL com/github/kornilova_l/flamegraph/proxy/StartData.setDuration (J)V
    ALOAD 1
    INVOKEVIRTUAL com/github/kornilova_l/flamegraph/proxy/StartData.getDuration ()J
    LCONST_1
    LCMP
    IFLE L21
    ACONST_NULL
    ALOAD 1
    INVOKEVIRTUAL com/github/kornilova_l/flamegraph/proxy/StartData.getStartTime ()J
    ALOAD 1
    INVOKEVIRTUAL com/github/kornilova_l/flamegraph/proxy/StartData.getDuration ()J
    ALOAD 1
    INVOKEVIRTUAL com/github/kornilova_l/flamegraph/proxy/StartData.getParameters ()[Ljava/lang/Object;
    INVOKESTATIC java/lang/Thread.currentThread ()Ljava/lang/Thread;
    LDC "com/github/kornilova_l/flamegraph/javaagent/generate/test_classes/HasCatch"
    LDC "main"
    LDC "([Ljava/lang/String;)V"
    ICONST_1
    LDC ""
    INVOKESTATIC com/github/kornilova_l/flamegraph/javaagent/logger/LoggerQueue.addToQueue (Ljava/lang/Object;JJ[Ljava/lang/Object;Ljava/lang/Thread;Ljava/lang/String;Ljava/lang/String;Ljava/lang/String;ZLjava/lang/String;)V
   L21
   FRAME SAME
    RETURN
   L14
   FRAME FULL [[Ljava/lang/String; com/github/kornilova_l/flamegraph/proxy/StartData] [java/lang/Throwable]
    ALOAD 1
    INVOKEVIRTUAL com/github/kornilova_l/flamegraph/proxy/StartData.isThrownByMethod ()Z
    IFNE L22
    ALOAD 1
    INVOKESTATIC java/lang/System.currentTimeMillis ()J
    INVOKEVIRTUAL com/github/kornilova_l/flamegraph/proxy/StartData.setDuration (J)V
    ALOAD 1
    INVOKEVIRTUAL com/github/kornilova_l/flamegraph/proxy/StartData.getDuration ()J
    LCONST_1
    LCMP
    IFLE L22
    DUP
    ICONST_1
    ALOAD 1
    INVOKEVIRTUAL com/github/kornilova_l/flamegraph/proxy/StartData.getStartTime ()J
    ALOAD 1
    INVOKEVIRTUAL com/github/kornilova_l/flamegraph/proxy/StartData.getDuration ()J
    ALOAD 1
    INVOKEVIRTUAL com/github/kornilova_l/flamegraph/proxy/StartData.getParameters ()[Ljava/lang/Object;
    INVOKESTATIC java/lang/Thread.currentThread ()Ljava/lang/Thread;
    LDC "com/github/kornilova_l/flamegraph/javaagent/generate/test_classes/HasCatch"
    LDC "main"
    LDC "([Ljava/lang/String;)V"
    ICONST_1
    LDC ""
    INVOKESTATIC com/github/kornilova_l/flamegraph/javaagent/logger/LoggerQueue.addToQueue (Ljava/lang/Throwable;ZJJ[Ljava/lang/Object;Ljava/lang/Thread;Ljava/lang/String;Ljava/lang/String;Ljava/lang/String;ZLjava/lang/String;)V
   L22
   FRAME SAME1 java/lang/Throwable
    ATHROW
    MAXSTACK = 14
    MAXLOCALS = 7
}
