// class version 52.0 (52)
// access flags 0x21
public class com/github/kornilova_l/flamegraph/javaagent/generate/test_classes/HasIf {


  // access flags 0x1
  public <init>()V
    ALOAD 0
    INVOKESPECIAL java/lang/Object.<init> ()V
    RETURN
    MAXSTACK = 1
    MAXLOCALS = 1

  // access flags 0x9
  public static main(I)I
    TRYCATCHBLOCK L0 L1 L1 java/lang/Throwable
    INVOKESTATIC java/lang/System.currentTimeMillis ()J
    ACONST_NULL
    INVOKESTATIC com/github/kornilova_l/flamegraph/javaagent/logger/LoggerQueue.createStartData (J[Ljava/lang/Object;)Lcom/github/kornilova_l/flamegraph/proxy/StartData;
    ASTORE 1
   L0
    ICONST_0
    ISTORE 2
    ILOAD 0
    IFLE L2
    IINC 2 1
   L2
   FRAME APPEND [com/github/kornilova_l/flamegraph/proxy/StartData I]
    ILOAD 2
    ALOAD 1
    INVOKESTATIC java/lang/System.currentTimeMillis ()J
    INVOKEVIRTUAL com/github/kornilova_l/flamegraph/proxy/StartData.setDuration (J)V
    ALOAD 1
    INVOKEVIRTUAL com/github/kornilova_l/flamegraph/proxy/StartData.getDuration ()J
    LCONST_1
    LCMP
    IFLE L3
    ACONST_NULL
    ALOAD 1
    INVOKEVIRTUAL com/github/kornilova_l/flamegraph/proxy/StartData.getStartTime ()J
    ALOAD 1
    INVOKEVIRTUAL com/github/kornilova_l/flamegraph/proxy/StartData.getDuration ()J
    ALOAD 1
    INVOKEVIRTUAL com/github/kornilova_l/flamegraph/proxy/StartData.getParameters ()[Ljava/lang/Object;
    INVOKESTATIC java/lang/Thread.currentThread ()Ljava/lang/Thread;
    LDC "com/github/kornilova_l/flamegraph/javaagent/generate/test_classes/HasIf"
    LDC "main"
    LDC "(I)I"
    ICONST_1
    LDC ""
    INVOKESTATIC com/github/kornilova_l/flamegraph/javaagent/logger/LoggerQueue.addToQueue (Ljava/lang/Object;JJ[Ljava/lang/Object;Ljava/lang/Thread;Ljava/lang/String;Ljava/lang/String;Ljava/lang/String;ZLjava/lang/String;)V
   L3
   FRAME SAME1 I
    IRETURN
   L1
   FRAME FULL [I com/github/kornilova_l/flamegraph/proxy/StartData] [java/lang/Throwable]
    ALOAD 1
    INVOKEVIRTUAL com/github/kornilova_l/flamegraph/proxy/StartData.isThrownByMethod ()Z
    IFNE L4
    ALOAD 1
    INVOKESTATIC java/lang/System.currentTimeMillis ()J
    INVOKEVIRTUAL com/github/kornilova_l/flamegraph/proxy/StartData.setDuration (J)V
    ALOAD 1
    INVOKEVIRTUAL com/github/kornilova_l/flamegraph/proxy/StartData.getDuration ()J
    LCONST_1
    LCMP
    IFLE L4
    DUP
    ICONST_0
    ALOAD 1
    INVOKEVIRTUAL com/github/kornilova_l/flamegraph/proxy/StartData.getStartTime ()J
    ALOAD 1
    INVOKEVIRTUAL com/github/kornilova_l/flamegraph/proxy/StartData.getDuration ()J
    ALOAD 1
    INVOKEVIRTUAL com/github/kornilova_l/flamegraph/proxy/StartData.getParameters ()[Ljava/lang/Object;
    INVOKESTATIC java/lang/Thread.currentThread ()Ljava/lang/Thread;
    LDC "com/github/kornilova_l/flamegraph/javaagent/generate/test_classes/HasIf"
    LDC "main"
    LDC "(I)I"
    ICONST_1
    LDC ""
    INVOKESTATIC com/github/kornilova_l/flamegraph/javaagent/logger/LoggerQueue.addToQueue (Ljava/lang/Throwable;ZJJ[Ljava/lang/Object;Ljava/lang/Thread;Ljava/lang/String;Ljava/lang/String;Ljava/lang/String;ZLjava/lang/String;)V
   L4
   FRAME SAME1 java/lang/Throwable
    ATHROW
    MAXSTACK = 14
    MAXLOCALS = 3
}
